README.rst
setup.py
channels_sendmail.egg-info/PKG-INFO
channels_sendmail.egg-info/SOURCES.txt
channels_sendmail.egg-info/dependency_links.txt
channels_sendmail.egg-info/top_level.txt
sendmail/__init__.py
sendmail/consumers.py
sendmail/routing.py
sendmail/wrap.py