Metadata-Version: 1.1
Name: channels-sendmail
Version: 0.0.1
Summary: Simple package to wrap Django's built-in `send_mail` function with channels
Home-page: https://github.com/albertoconnor/channels-sendmail
Author: Albert O'Connor
Author-email: albert@albertoconnor.ca
License: MIT
Platform: UNKNOWN
Classifier: Development Status :: 3 - Alpha
Classifier: Intended Audience :: Developers
Classifier: License :: OSI Approved :: MIT License
Classifier: Programming Language :: Python :: 2
Classifier: Programming Language :: Python :: 2.7
Classifier: Programming Language :: Python :: 3
Classifier: Programming Language :: Python :: 3.4
Classifier: Programming Language :: Python :: 3.5
